rex.py
rexutil-1.0.5.dist-info/DESCRIPTION.rst
rexutil-1.0.5.dist-info/METADATA
rexutil-1.0.5.dist-info/metadata.json
rexutil-1.0.5.dist-info/RECORD
rexutil-1.0.5.dist-info/top_level.txt
rexutil-1.0.5.dist-info/WHEEL
