Metadata-Version: 2.0
Name: rexutil
Version: 1.0.5
Summary: A python module for regular expression manipulations.
Home-page: https://github.com/bdastur/rex
Author: Behzad Dastur
Author-email: bdastur@gmail.com
License: Apache Software License
Keywords: re regular expression utility matching development
Platform: UNKNOWN
